{"cameraMode":{"drawMode":0,"name":"Shaded","section":"Shading Mode"},"sceneLighting":true,"audioPlay":false,"sceneViewState":{"m_AlwaysRefresh":true,"showFog":true,"showSkybox":true,"showFlares":true,"showImageEffects":true,"showParticleSystems":true,"showVisualEffectGraphs":true,"m_FxEnabled":true},"in2DMode":false,"pivot":{"x":2.7495312690734865,"y":5.551068305969238,"z":-10.746809005737305},"rotation":{"x":-0.3477638363838196,"y":0.05442802235484123,"z":-0.020227588713169099,"w":-0.9357881546020508},"size":10.0,"orthographic":false}